resume_yaml_builder/__init__.py
resume_yaml_builder/main.py
resume_yaml_builder/prompts.py
resume_yaml_builder-2025.12.21142031.dist-info/METADATA
resume_yaml_builder-2025.12.21142031.dist-info/WHEEL
resume_yaml_builder-2025.12.21142031.dist-info/top_level.txt
resume_yaml_builder-2025.12.21142031.dist-info/RECORD
