Metadata-Version: 2.4
Name: resume-yaml-builder
Version: 2025.12.21142031
Summary: A new package that leverages language models to transform structured YAML data into well-formatted resume PDFs. Users provide their resume details in YAML format, and the package extracts key informat
Author-email: resume-yaml-builder <hi@eugene.plus>
License: MIT
Project-URL: Homepage, https://github.com/chigwell/resume-yaml-builder
Requires-Python: >=3.9
Requires-Dist: langchain-llm7>=0.0.0
Requires-Dist: llmatch-messages>=0.0.0
Requires-Dist: langchain-core>=0.3.0
